wasmtime/__init__.py
wasmtime/_bindings.py
wasmtime/_config.py
wasmtime/_engine.py
wasmtime/_error.py
wasmtime/_exportable.py
wasmtime/_extern.py
wasmtime/_ffi.py
wasmtime/_func.py
wasmtime/_globals.py
wasmtime/_instance.py
wasmtime/_linker.py
wasmtime/_managed.py
wasmtime/_memory.py
wasmtime/_module.py
wasmtime/_sharedmemory.py
wasmtime/_slab.py
wasmtime/_store.py
wasmtime/_table.py
wasmtime/_trap.py
wasmtime/_types.py
wasmtime/_value.py
wasmtime/_wasi.py
wasmtime/_wat2wasm.py
wasmtime/py.typed
wasmtime/component/__init__.py
wasmtime/component/_component.py
wasmtime/component/_enter.py
wasmtime/component/_func.py
wasmtime/component/_instance.py
wasmtime/component/_linker.py
wasmtime/component/_resource_type.py
wasmtime/component/_resources.py
wasmtime/component/_types.py
wasmtime/win32-x86_64/_wasmtime.dll
wasmtime-40.0.0.dist-info/licenses/LICENSE
wasmtime-40.0.0.dist-info/METADATA
wasmtime-40.0.0.dist-info/WHEEL
wasmtime-40.0.0.dist-info/top_level.txt
wasmtime-40.0.0.dist-info/RECORD
