Metadata-Version: 2.4
Name: wasmtime
Version: 40.0.0
Summary: A WebAssembly runtime powered by Wasmtime
Author-email: The Wasmtime Project Developers <hello@bytecodealliance.org>
License-Expression: Apache-2.0 WITH LLVM-exception
Project-URL: Homepage, https://github.com/bytecodealliance/wasmtime-py
Project-URL: Bug Tracker, https://github.com/bytecodealliance/wasmtime-py/issues
Project-URL: Documentation, https://bytecodealliance.github.io/wasmtime-py/
Project-URL: Source Code, https://github.com/bytecodealliance/wasmtime-py
Classifier: Programming Language :: Python
Classifier: Programming Language :: Python :: 3
Classifier: Programming Language :: Python :: 3.9
Classifier: Programming Language :: Python :: 3.10
Classifier: Programming Language :: Python :: 3.11
Classifier: Programming Language :: Python :: 3.12
Classifier: Programming Language :: Python :: 3.13
Classifier: Programming Language :: Python :: 3.14
Classifier: Programming Language :: Python :: Implementation :: CPython
Classifier: Programming Language :: Python :: Implementation :: PyPy
Classifier: Programming Language :: Rust
Classifier: Topic :: Software Development :: Compilers
Classifier: Topic :: Software Development :: Interpreters
Requires-Python: >=3.9
License-File: LICENSE
Provides-Extra: testing
Requires-Dist: coverage; extra == "testing"
Requires-Dist: pycparser; extra == "testing"
Requires-Dist: pytest-mypy; extra == "testing"
Requires-Dist: pytest; extra == "testing"
Dynamic: license-file
